uz_en_dictionary/__init__.py
uz_en_dictionary/dicts.py
uz_en_dictionary/getbase.py
uz_en_dictionary/database/controller.py
uz_en_dictionary/database/en-uz/a.json
uz_en_dictionary/database/en-uz/b.json
uz_en_dictionary/database/en-uz/c.json
uz_en_dictionary/database/en-uz/d.json
uz_en_dictionary/database/en-uz/e.json
uz_en_dictionary/database/en-uz/f.json
uz_en_dictionary/database/en-uz/g.json
uz_en_dictionary/database/en-uz/h.json
uz_en_dictionary/database/en-uz/i.json
uz_en_dictionary/database/en-uz/j.json
uz_en_dictionary/database/en-uz/k.json
uz_en_dictionary/database/en-uz/l.json
uz_en_dictionary/database/en-uz/m.json
uz_en_dictionary/database/en-uz/n.json
uz_en_dictionary/database/en-uz/o.json
uz_en_dictionary/database/en-uz/p.json
uz_en_dictionary/database/en-uz/q.json
uz_en_dictionary/database/en-uz/r.json
uz_en_dictionary/database/en-uz/s.json
uz_en_dictionary/database/en-uz/t.json
uz_en_dictionary/database/en-uz/u.json
uz_en_dictionary/database/en-uz/v.json
uz_en_dictionary/database/en-uz/w.json
uz_en_dictionary/database/en-uz/x.json
uz_en_dictionary/database/en-uz/y.json
uz_en_dictionary/database/en-uz/z.json
uz_en_dictionary/database/uz-en/a.json
uz_en_dictionary/database/uz-en/b.json
uz_en_dictionary/database/uz-en/c.json
uz_en_dictionary/database/uz-en/d.json
uz_en_dictionary/database/uz-en/e.json
uz_en_dictionary/database/uz-en/f.json
uz_en_dictionary/database/uz-en/g.json
uz_en_dictionary/database/uz-en/h.json
uz_en_dictionary/database/uz-en/i.json
uz_en_dictionary/database/uz-en/j.json
uz_en_dictionary/database/uz-en/k.json
uz_en_dictionary/database/uz-en/l.json
uz_en_dictionary/database/uz-en/m.json
uz_en_dictionary/database/uz-en/n.json
uz_en_dictionary/database/uz-en/o.json
uz_en_dictionary/database/uz-en/p.json
uz_en_dictionary/database/uz-en/q.json
uz_en_dictionary/database/uz-en/r.json
uz_en_dictionary/database/uz-en/s.json
uz_en_dictionary/database/uz-en/t.json
uz_en_dictionary/database/uz-en/u.json
uz_en_dictionary/database/uz-en/v.json
uz_en_dictionary-0.0.4.dist-info/LICENSE
uz_en_dictionary-0.0.4.dist-info/METADATA
uz_en_dictionary-0.0.4.dist-info/WHEEL
uz_en_dictionary-0.0.4.dist-info/top_level.txt
uz_en_dictionary-0.0.4.dist-info/RECORD
