Metadata-Version: 2.1
Name: uz_en_dictionary
Version: 0.0.4
Summary: Simple Uzbek-English Dictionary
Home-page: https://github.com/matyokubov/uzEn_pkg
Author: Firdavs
Author-email: firdavsmatyoqubov@mail.ru
Project-URL: Bug Tracker, https://github.com/matyokubov/uzEn_pkg/issues
Classifier: Programming Language :: Python :: 3
Classifier: License :: OSI Approved :: MIT License
Classifier: Operating System :: OS Independent
License-File: LICENSE
